local_notebooklm/__init__.py
local_notebooklm/config.py
local_notebooklm/processor.py
local_notebooklm/server.py
local_notebooklm/start.py
local_notebooklm/version.py
local_notebooklm/steps/__init__.py
local_notebooklm/steps/helpers.py
local_notebooklm/steps/prompts.py
local_notebooklm/steps/step1.py
local_notebooklm/steps/step2.py
local_notebooklm/steps/step3.py
local_notebooklm/steps/step4.py
local_notebook-0.1.0.dist-info/METADATA
local_notebook-0.1.0.dist-info/WHEEL
local_notebook-0.1.0.dist-info/top_level.txt
local_notebook-0.1.0.dist-info/RECORD
