Metadata-Version: 2.2
Name: local-notebook
Version: 0.1.0
Summary: A local notebook implementation
Home-page: https://github.com/Goekdeniz-Guelmez/Local-NotebookLM
Author: Gökdeniz Gülmez
Author-email: Gökdeniz Gülmez <goekdenizguelmez@gmail.com>
License: Apache-2.0
Project-URL: Homepage, https://github.com/Goekdeniz-Guelmez//Local-NotebookLM
Project-URL: Bug Tracker, https://github.com/Goekdeniz-Guelmez//Local-NotebookLM/issues
Classifier: Programming Language :: Python :: 3.12
Classifier: License :: OSI Approved :: Apache Software License
Classifier: Operating System :: OS Independent
Requires-Python: >=3.12
Dynamic: author
Dynamic: home-page
Dynamic: requires-python
